newsy/__init__.py
newsy/newsy.py
newsy-0.1.2.dist-info/METADATA
newsy-0.1.2.dist-info/WHEEL
newsy-0.1.2.dist-info/entry_points.txt
newsy-0.1.2.dist-info/top_level.txt
newsy-0.1.2.dist-info/RECORD
