Metadata-Version: 2.1
Name: newsy
Version: 0.1.2
Summary: Summarize news articles on a given topic
Author: Gowner Jones
License: UNKNOWN
Platform: UNKNOWN
Classifier: Development Status :: 3 - Alpha
Classifier: License :: OSI Approved :: MIT License
Classifier: Programming Language :: Python :: 3
Classifier: Programming Language :: Python :: 3.6
Classifier: Programming Language :: Python :: 3.7
Classifier: Programming Language :: Python :: 3.8
Classifier: Programming Language :: Python :: 3.9
Requires-Dist: newspaper3k
Requires-Dist: transformers
Requires-Dist: GoogleNews
